cloudmesh_timeseries-4.3.3-py3.8-nspkg.pth
cloudmesh/timeseries/__init__.py
cloudmesh/timeseries/__version__.py
cloudmesh/timeseries/metric.py
cloudmesh/timeseries/transform.py
cloudmesh/timeseries/widgets.py
cloudmesh_timeseries-4.3.3.dist-info/LICENSE
cloudmesh_timeseries-4.3.3.dist-info/METADATA
cloudmesh_timeseries-4.3.3.dist-info/WHEEL
cloudmesh_timeseries-4.3.3.dist-info/namespace_packages.txt
cloudmesh_timeseries-4.3.3.dist-info/top_level.txt
cloudmesh_timeseries-4.3.3.dist-info/RECORD
