Metadata-Version: 2.1
Name: cloudmesh-timeseries
Version: 4.3.3
Summary: A command called timeseries and foo for the cloudmesh shell
Home-page: https://github.com/cloudmesh/cloudmesh-timeseries
Author: Gregor von Laszewski
Author-email: laszewski@gmail.com
License: Apache 2.0
Platform: UNKNOWN
Classifier: Development Status :: 5 - Production/Stable
Classifier: Environment :: Web Environment
Classifier: Intended Audience :: Developers
Classifier: License :: OSI Approved :: BSD License
Classifier: Operating System :: OS Independent
Classifier: Programming Language :: Python
Classifier: Programming Language :: Python :: 3
Classifier: Programming Language :: Python :: 3.7
Classifier: Programming Language :: Python :: 3.8
Requires-Dist: ipython
Requires-Dist: ipywidgets
